python_analysis/__init__.py
python_analysis/cleaning.py
python_analysis/setup.py
python_analysis/statistics.py
python_analysis/visualization.py
test_analysis/__init__.py
test_analysis/test_cleaning.py
test_analysis/test_statistics.py
test_analysis/test_visualization.py
python_analysis-0.1.dist-info/METADATA
python_analysis-0.1.dist-info/WHEEL
python_analysis-0.1.dist-info/top_level.txt
python_analysis-0.1.dist-info/RECORD
